.travis.yml
licence
readme.md
requirements-dev.txt
requirements.txt
setup.cfg
setup.py
tox.ini
devrepo.egg-info/PKG-INFO
devrepo.egg-info/SOURCES.txt
devrepo.egg-info/dependency_links.txt
devrepo.egg-info/not-zip-safe
devrepo.egg-info/pbr.json
devrepo.egg-info/top_level.txt
src/readme.md
src/main/devrepo/__init__.py
src/main/devrepo/config.ini
src/main/devrepo/config.py
src/main/devrepo/register.py
src/main/devrepo/shell.py
src/test/devrepo_test/__init__.py
src/test/devrepo_test/config_test.py
src/test/devrepo_test/register_test.py
src/test/devrepo_test/shell_test.py
src/verify/user_code/__init__.py
src/verify/user_code/main_stack.py
src/verify/user_code/test_stack.py
tool/arkon.sh
tool/github_squash.py
tool/perform_tox.sh
tool/provision_env.sh
tool/readme.md
tool/release_update.py