Metadata-Version: 2.1
Name: devrepo
Version: 0.2.0.dev1
Summary: development repository operations
Home-page: https://github.com/random-python/devrepo
Author: Andrei Pozolotin
Author-email: andrei.pozolotin@gmail.com
License: Apache-2
Keywords: development,repository,operations
Platform: UNKNOWN
Classifier: Development Status :: 4 - Beta
Classifier: Intended Audience :: Developers
Classifier: License :: OSI Approved :: Apache Software License
Classifier: Programming Language :: Python
Classifier: Programming Language :: Python :: 3.8
Classifier: Programming Language :: Python :: 3.9
Classifier: Programming Language :: Python :: 3.10
Requires-Python: >=3.8
